{
	"success": true,
	"data": {
		"csjx": [{
			"score": "2",
			"street": "甪直镇",
			"x": "13455281",
			"y": "3645840",
			"rank": "14",
			"streetID": 102,
			"topN": ""
		}, {
			"score": "3",
			"street": "金庭镇",
			"x": "13391808",
			"y": "3628235",
			"rank": "13",
			"streetID": 108,
			"topN": ""
		}, {
			"score": "4",
			"street": "越溪街道",
			"x": "13421405",
			"y": "3639052",
			"rank": "12",
			"streetID": 104,
			"topN": ""
		}, {
			"score": "5",
			"street": "东山镇",
			"x": "13403861",
			"y": "3620434",
			"rank": "11",
			"streetID": 106,
			"topN": ""
		}, {
			"score": "6",
			"street": "木渎镇",
			"x": "13416874",
			"y": "3646248",
			"rank": "10",
			"streetID": 103,
			"topN": ""
		}, {
			"score": "7",
			"street": "胥口镇",
			"x": "13413291",
			"y": "3642265",
			"rank": "9",
			"streetID": 107,
			"topN": ""
		}, {
			"score": "8",
			"street": "郭巷街道",
			"x": "13436796",
			"y": "3642021",
			"rank": "8",
			"streetID": 111,
			"topN": ""
		}, {
			"score": "9",
			"street": "高新区",
			"x": "13428044",
			"y": "3645079",
			"rank": "7",
			"streetID": 113,
			"topN": "绿化带内无生活垃圾、建筑垃圾。\n绿化带内无生活垃圾、建筑垃圾。\n工地出入口地面硬化"
		}, {
			"score": "10",
			"street": "横泾街道",
			"x": "13419044",
			"y": "3632853",
			"rank": "6",
			"streetID": 101,
			"topN": ""
		}, {
			"score": "11",
			"street": "光福镇",
			"x": "13402903",
			"y": "3649195",
			"rank": "5",
			"streetID": 105,
			"topN": ""
		}, {
			"score": "12",
			"street": "香山街道",
			"x": "13405632",
			"y": "3642705",
			"rank": "4",
			"streetID": 109,
			"topN": ""
		}, {
			"score": "13",
			"street": "临湖镇",
			"x": "13413453",
			"y": "3630343",
			"rank": "3",
			"streetID": 110,
			"topN": ""
		}, {
			"score": "14",
			"street": "城南街道",
			"x": "13430550",
			"y": "3642880",
			"rank": "5",
			"streetID": 112,
			"topN": ""
		}, {
			"score": "15",
			"street": "太湖新城",
			"x": "13424963",
			"y": "3635279",
			"rank": "1",
			"streetID": 100,
			"topN": ""
		}],
		"rec": [{
			"street": "太湖新城",
			"inst": "",
			"x": "13424963",
			"y": "3635279",
			"archive": "",
			"streetID": 100,
			"inc": ""
		}, {
			"street": "横泾街道",
			"inst": "",
			"x": "13419044",
			"y": "3632853",
			"archive": "",
			"streetID": 101,
			"inc": ""
		}, {
			"street": "甪直镇",
			"inst": "",
			"x": "13455281",
			"y": "3645840",
			"archive": "",
			"streetID": 102,
			"inc": ""
		}, {
			"street": "木渎镇",
			"inst": "",
			"x": "13416874",
			"y": "3646248",
			"archive": "",
			"streetID": 103,
			"inc": ""
		}, {
			"street": "越溪街道",
			"inst": "",
			"x": "13421405",
			"y": "3639052",
			"archive": "",
			"streetID": 104,
			"inc": ""
		}, {
			"street": "光福镇",
			"inst": "",
			"x": "13402903",
			"y": "3649195",
			"archive": "",
			"streetID": 105,
			"inc": ""
		}, {
			"street": "东山镇",
			"inst": "",
			"x": "13403861",
			"y": "3620434",
			"archive": "",
			"streetID": 106,
			"inc": ""
		}, {
			"street": "胥口镇",
			"inst": "",
			"x": "13413291",
			"y": "3642265",
			"archive": "",
			"streetID": 107,
			"inc": ""
		}, {
			"street": "金庭镇",
			"inst": "",
			"x": "13391808",
			"y": "3628235",
			"archive": "",
			"streetID": 108,
			"inc": ""
		}, {
			"street": "香山街道",
			"inst": "",
			"x": "13405632",
			"y": "3642705",
			"archive": "",
			"streetID": 109,
			"inc": ""
		}, {
			"street": "临湖镇",
			"inst": "",
			"x": "13413453",
			"y": "3630343",
			"archive": "",
			"streetID": 110,
			"inc": ""
		}, {
			"street": "郭巷街道",
			"inst": "",
			"x": "13436796",
			"y": "3642021",
			"archive": "",
			"streetID": 111,
			"inc": ""
		}, {
			"street": "城南街道",
			"inst": 0,
			"x": "13430550",
			"y": "3642880",
			"archive": 0,
			"streetID": 112,
			"inc": ""
		}, {
			"street": "高新区",
			"inst": "",
			"x": "13428044",
			"y": "3645079",
			"archive": "",
			"streetID": 113,
			"inc": ""
		}],
		"ds_5": [{
			"score": "0",
			"street": "甪直镇",
			"x": "13455281",
			"y": "3645840",
			"streetID": 102
		}, {
			"score": "3",
			"street": "金庭镇",
			"x": "13391808",
			"y": "3628235",
			"streetID": 108
		}, {
			"score": "4",
			"street": "越溪街道",
			"x": "13421405",
			"y": "3639052",
			"streetID": 104
		}, {
			"score": "5",
			"street": "东山镇",
			"x": "13403861",
			"y": "3620434",
			"streetID": 106
		}, {
			"score": "6",
			"street": "木渎镇",
			"x": "13416874",
			"y": "3646248",
			"streetID": 103
		}, {
			"score": "7",
			"street": "胥口镇",
			"x": "13413291",
			"y": "3642265",
			"streetID": 107
		}, {
			"score": "8",
			"street": "郭巷街道",
			"x": "13436796",
			"y": "3642021",
			"streetID": 111
		}, {
			"score": "9",
			"street": "高新区",
			"x": "13428044",
			"y": "3645079",
			"streetID": 113
		}, {
			"score": "10",
			"street": "横泾街道",
			"x": "13419044",
			"y": "3632853",
			"streetID": 101
		}, {
			"score": "11",
			"street": "光福镇",
			"x": "13402903",
			"y": "3649195",
			"streetID": 105
		}, {
			"score": "12",
			"street": "香山街道",
			"x": "13405632",
			"y": "3642705",
			"streetID": 109
		}, {
			"score": "13",
			"street": "临湖镇",
			"x": "13413453",
			"y": "3630343",
			"streetID": 110
		}, {
			"score": "14",
			"street": "城南街道",
			"x": "13430550",
			"y": "3642880",
			"streetID": 112
		}, {
			"score": "15",
			"street": "太湖新城",
			"x": "13424963",
			"y": "3635279",
			"streetID": 100
		}],
		"ds_4": [{
			"score": "0",
			"street": "甪直镇",
			"x": "13455281",
			"y": "3645840",
			"streetID": 102
		}, {
			"score": "3",
			"street": "金庭镇",
			"x": "13391808",
			"y": "3628235",
			"streetID": 108
		}, {
			"score": "4",
			"street": "越溪街道",
			"x": "13421405",
			"y": "3639052",
			"streetID": 104
		}, {
			"score": "5",
			"street": "东山镇",
			"x": "13403861",
			"y": "3620434",
			"streetID": 106
		}, {
			"score": "6",
			"street": "木渎镇",
			"x": "13416874",
			"y": "3646248",
			"streetID": 103
		}, {
			"score": "7",
			"street": "胥口镇",
			"x": "13413291",
			"y": "3642265",
			"streetID": 107
		}, {
			"score": "8",
			"street": "郭巷街道",
			"x": "13436796",
			"y": "3642021",
			"streetID": 111
		}, {
			"score": "9",
			"street": "高新区",
			"x": "13428044",
			"y": "3645079",
			"streetID": 113
		}, {
			"score": "10",
			"street": "横泾街道",
			"x": "13419044",
			"y": "3632853",
			"streetID": 101
		}, {
			"score": "11",
			"street": "光福镇",
			"x": "13402903",
			"y": "3649195",
			"streetID": 105
		}, {
			"score": "12",
			"street": "香山街道",
			"x": "13405632",
			"y": "3642705",
			"streetID": 109
		}, {
			"score": "13",
			"street": "临湖镇",
			"x": "13413453",
			"y": "3630343",
			"streetID": 110
		}, {
			"score": "14",
			"street": "城南街道",
			"x": "13430550",
			"y": "3642880",
			"streetID": 112
		}, {
			"score": "15",
			"street": "太湖新城",
			"x": "13424963",
			"y": "3635279",
			"streetID": 100
		}],
		"ds_3": [{
			"score": "0",
			"street": "甪直镇",
			"x": "13455281",
			"y": "3645840",
			"streetID": 102
		}, {
			"score": "3",
			"street": "金庭镇",
			"x": "13391808",
			"y": "3628235",
			"streetID": 108
		}, {
			"score": "4",
			"street": "越溪街道",
			"x": "13421405",
			"y": "3639052",
			"streetID": 104
		}, {
			"score": "5",
			"street": "东山镇",
			"x": "13403861",
			"y": "3620434",
			"streetID": 106
		}, {
			"score": "6",
			"street": "木渎镇",
			"x": "13416874",
			"y": "3646248",
			"streetID": 103
		}, {
			"score": "7",
			"street": "胥口镇",
			"x": "13413291",
			"y": "3642265",
			"streetID": 107
		}, {
			"score": "8",
			"street": "郭巷街道",
			"x": "13436796",
			"y": "3642021",
			"streetID": 111
		}, {
			"score": "9",
			"street": "高新区",
			"x": "13428044",
			"y": "3645079",
			"streetID": 113
		}, {
			"score": "10",
			"street": "横泾街道",
			"x": "13419044",
			"y": "3632853",
			"streetID": 101
		}, {
			"score": "11",
			"street": "光福镇",
			"x": "13402903",
			"y": "3649195",
			"streetID": 105
		}, {
			"score": "12",
			"street": "香山街道",
			"x": "13405632",
			"y": "3642705",
			"streetID": 109
		}, {
			"score": "13",
			"street": "临湖镇",
			"x": "13413453",
			"y": "3630343",
			"streetID": 110
		}, {
			"score": "14",
			"street": "城南街道",
			"x": "13430550",
			"y": "3642880",
			"streetID": 112
		}, {
			"score": "15",
			"street": "太湖新城",
			"x": "13424963",
			"y": "3635279",
			"streetID": 100
		}],
		"ds_2": [{
			"score": "0",
			"street": "甪直镇",
			"x": "13455281",
			"y": "3645840",
			"streetID": 102
		}, {
			"score": "3",
			"street": "金庭镇",
			"x": "13391808",
			"y": "3628235",
			"streetID": 108
		}, {
			"score": "4",
			"street": "越溪街道",
			"x": "13421405",
			"y": "3639052",
			"streetID": 104
		}, {
			"score": "5",
			"street": "东山镇",
			"x": "13403861",
			"y": "3620434",
			"streetID": 106
		}, {
			"score": "6",
			"street": "木渎镇",
			"x": "13416874",
			"y": "3646248",
			"streetID": 103
		}, {
			"score": "7",
			"street": "胥口镇",
			"x": "13413291",
			"y": "3642265",
			"streetID": 107
		}, {
			"score": "8",
			"street": "郭巷街道",
			"x": "13436796",
			"y": "3642021",
			"streetID": 111
		}, {
			"score": "9",
			"street": "高新区",
			"x": "13428044",
			"y": "3645079",
			"streetID": 113
		}, {
			"score": "10",
			"street": "横泾街道",
			"x": "13419044",
			"y": "3632853",
			"streetID": 101
		}, {
			"score": "11",
			"street": "光福镇",
			"x": "13402903",
			"y": "3649195",
			"streetID": 105
		}, {
			"score": "12",
			"street": "香山街道",
			"x": "13405632",
			"y": "3642705",
			"streetID": 109
		}, {
			"score": "13",
			"street": "临湖镇",
			"x": "13413453",
			"y": "3630343",
			"streetID": 110
		}, {
			"score": "14",
			"street": "城南街道",
			"x": "13430550",
			"y": "3642880",
			"streetID": 112
		}, {
			"score": "15",
			"street": "太湖新城",
			"x": "13424963",
			"y": "3635279",
			"streetID": 100
		}],
		"ds_1": [{
			"score": "0",
			"street": "东山镇",
			"x": "13403861",
			"y": "3620434",
			"streetID": 106
		}, {
			"score": "0",
			"street": "甪直镇",
			"x": "13455281",
			"y": "3645840",
			"streetID": 102
		}, {
			"score": "3",
			"street": "金庭镇",
			"x": "13391808",
			"y": "3628235",
			"streetID": 108
		}, {
			"score": "4",
			"street": "越溪街道",
			"x": "13421405",
			"y": "3639052",
			"streetID": 104
		}, {
			"score": "6",
			"street": "木渎镇",
			"x": "13416874",
			"y": "3646248",
			"streetID": 103
		}, {
			"score": "7",
			"street": "胥口镇",
			"x": "13413291",
			"y": "3642265",
			"streetID": 107
		}, {
			"score": "8",
			"street": "郭巷街道",
			"x": "13436796",
			"y": "3642021",
			"streetID": 111
		}, {
			"score": "9",
			"street": "高新区",
			"x": "13428044",
			"y": "3645079",
			"streetID": 113
		}, {
			"score": "10",
			"street": "横泾街道",
			"x": "13419044",
			"y": "3632853",
			"streetID": 101
		}, {
			"score": "11",
			"street": "光福镇",
			"x": "13402903",
			"y": "3649195",
			"streetID": 105
		}, {
			"score": "12",
			"street": "香山街道",
			"x": "13405632",
			"y": "3642705",
			"streetID": 109
		}, {
			"score": "13",
			"street": "临湖镇",
			"x": "13413453",
			"y": "3630343",
			"streetID": 110
		}, {
			"score": "14",
			"street": "城南街道",
			"x": "13430550",
			"y": "3642880",
			"streetID": 112
		}, {
			"score": "15",
			"street": "太湖新城",
			"x": "13424963",
			"y": "3635279",
			"streetID": 100
		}]
	}
}
